domnode/__init__.py
domnode/node.py
domnode/filters/__init__.py
domnode/filters/preset/__init__.py
domnode/filters/preset/all.py
domnode/filters/preset/semantic.py
domnode/filters/preset/visible.py
domnode/filters/semantic/__init__.py
domnode/filters/semantic/attributes.py
domnode/filters/semantic/empty.py
domnode/filters/semantic/presentational.py
domnode/filters/semantic/wrappers.py
domnode/filters/visibility/__init__.py
domnode/filters/visibility/css_hidden.py
domnode/filters/visibility/non_visible_tags.py
domnode/filters/visibility/zero_dimensions.py
domnode/parsers/__init__.py
domnode/parsers/cdp.py
domnode/parsers/html.py
domnode-0.2.0.dist-info/licenses/LICENSE
domnode-0.2.0.dist-info/METADATA
domnode-0.2.0.dist-info/WHEEL
domnode-0.2.0.dist-info/top_level.txt
domnode-0.2.0.dist-info/RECORD
