Metadata-Version: 2.4
Name: domnode
Version: 0.2.0
Summary: DOM nodes with browser rendering data for web automation
Author-email: Steve Wang <steve.z.wang@gmail.com>
License: MIT
Project-URL: Homepage, https://github.com/steve-z-wang/domnode
Project-URL: Repository, https://github.com/steve-z-wang/domnode
Project-URL: Issues, https://github.com/steve-z-wang/domnode/issues
Project-URL: Changelog, https://github.com/steve-z-wang/domnode/releases
Keywords: dom,html,parser,web-automation,browser,cdp,selenium,playwright,puppeteer,web-scraping
Classifier: Development Status :: 4 - Beta
Classifier: Intended Audience :: Developers
Classifier: License :: OSI Approved :: MIT License
Classifier: Operating System :: OS Independent
Classifier: Programming Language :: Python :: 3
Classifier: Programming Language :: Python :: 3.9
Classifier: Programming Language :: Python :: 3.10
Classifier: Programming Language :: Python :: 3.11
Classifier: Programming Language :: Python :: 3.12
Classifier: Programming Language :: Python :: 3.13
Classifier: Topic :: Software Development :: Libraries :: Python Modules
Classifier: Topic :: Internet :: WWW/HTTP :: Browsers
Classifier: Topic :: Text Processing :: Markup :: HTML
Requires-Python: >=3.9
License-File: LICENSE
Requires-Dist: lxml>=4.9.0
Provides-Extra: dev
Requires-Dist: pytest>=7.0.0; extra == "dev"
Requires-Dist: pytest-cov>=4.0.0; extra == "dev"
Dynamic: license-file
